[
    {
        "source": "G1",
        "title": "Coreia do Norte afirma que ataques dos EUA à Venezuela são 'forma grave de violação de soberania' - G1",
        "timestamp": "2026-01-04T10:16:53Z"
    },
    {
        "source": "CNN Brasil",
        "title": "Brasil defende resolução sem \"ingerência externa\" na Venezuela - CNN Brasil",
        "timestamp": "2026-01-04T16:46:20Z"
    },
    {
        "source": "Nexo Jornal",
        "title": "O interesse americano no petróleo da Venezuela - Nexo Jornal",
        "timestamp": "2026-01-03T21:57:16Z"
    },
    {
        "source": "Centro de Operações Rio",
        "title": "Município do Rio de Janeiro entrou em ESTÁGIO 2 às 08h07 deste domingo, 04 de janeiro de 2026 - Centro de Operações Rio",
        "timestamp": "2026-01-04T11:11:58Z"
    },
    {
        "source": "Agência Brasil",
        "title": "Papa defende bem-estar do povo venezuelano e a soberania do país - Agência Brasil",
        "timestamp": "2026-01-04T13:32:00Z"
    },
    {
        "source": "Agência Brasil",
        "title": "Carnaval não oficial abre pré-folia neste domingo no Rio - Agência Brasil",
        "timestamp": "2026-01-04T10:02:00Z"
    }
]