[
    {
        "source": "Poder360",
        "title": "Castro cita voto de Moraes sobre quando uso da força é \"necessário\" - Poder360",
        "timestamp": "2025-11-03T22:51:29Z"
    },
    {
        "source": "Coluna do Fla",
        "title": "Presidente do Flamengo se encontra com príncipe da Inglaterra; entenda o motivo - Coluna do Fla",
        "timestamp": "2025-11-03T23:24:35Z"
    },
    {
        "source": "CartaCapital",
        "title": "PL aciona o Centrão para tentar emplacar Flávio Bolsonaro na presidência da CPI do Crime Organizado - CartaCapital",
        "timestamp": "2025-11-03T14:32:00Z"
    },
    {
        "source": "O Globo",
        "title": "Homicídio, tráfico, estupro coletivo: veja os crimes atribuídos pela polícia aos mortos na operação no Alemão e na Penha - O Globo",
        "timestamp": "2025-11-03T14:22:54Z"
    },
    {
        "source": "Jornal da Cidade Online",
        "title": "Castro prepara o “golpe de misericórdia” - Jornal da Cidade Online",
        "timestamp": "2025-11-03T22:57:00Z"
    },
    {
        "source": "Poder360",
        "title": "Mauro Cid retira tornozeleira eletrônica e inicia cumprimento de pena - Poder360",
        "timestamp": "2025-11-03T19:06:16Z"
    }
]