[
    {
        "source": "G1",
        "title": "Dinamarca e Groenlândia rejeitam tentativa de controle dos EUA após Trump nomear enviado especial - G1",
        "timestamp": "2025-12-22T13:14:57Z"
    },
    {
        "source": "Agência Brasil",
        "title": "Dino suspende trecho de PL que libera emendas do orçamento secreto - Agência Brasil",
        "timestamp": "2025-12-21T21:15:00Z"
    },
    {
        "source": "CNN Brasil",
        "title": "General russo morre em atentado com carro-bomba em Moscou, diz comitê - CNN Brasil",
        "timestamp": "2025-12-22T09:23:06Z"
    },
    {
        "source": "Notícias da TV",
        "title": "Paolla Oliveira e Diogo Nogueira anunciam separação após quase 5 anos juntos - Notícias da TV",
        "timestamp": "2025-12-22T13:29:00Z"
    },
    {
        "source": "Defesa Civil do Rio Grande do Sul",
        "title": "Defesa Civil alerta: Condição de ALERTA para instabilidades que atuam na Região Metropolitana de Porto Alegre - Defesa Civil do Rio Grande do Sul",
        "timestamp": "2025-12-21T23:46:53Z"
    },
    {
        "source": "Agência Brasil",
        "title": "Receita abre consulta a lote residual do Imposto de Renda - Agência Brasil",
        "timestamp": "2025-12-22T13:37:00Z"
    }
]