[
    {
        "source": "BBC",
        "title": "EUA dizem que bloqueio naval ao estreito de Ormuz começará em poucas horas e preço do petróleo dispara novamente - BBC",
        "timestamp": "2026-04-13T10:11:16Z"
    },
    {
        "source": "Metrópoles",
        "title": "O recado de Alcolumbre a Messias antes da votação para o STF - Metrópoles",
        "timestamp": "2026-04-13T08:00:33Z"
    },
    {
        "source": "Correio Braziliense",
        "title": "Papa diz que não tem intenção de entrar em debate com Trump e fala sobre paz - Correio Braziliense",
        "timestamp": "2026-04-13T09:44:00Z"
    },
    {
        "source": "Poder360",
        "title": "PT minimiza empate de Flávio e culpa INSS e Master pelo desgaste - Poder360",
        "timestamp": "2026-04-12T01:36:52Z"
    },
    {
        "source": "CNN Brasil",
        "title": "Keiko Fujimori lidera a votação no Peru com 37% das urnas apuradas - CNN Brasil",
        "timestamp": "2026-04-13T06:04:20Z"
    },
    {
        "source": "Brasil 247",
        "title": "Centrão vê Zema como “bomba eleitoral” após falas sobre Nordeste - Brasil 247",
        "timestamp": "2026-04-13T12:10:24Z"
    }
]