[
    {
        "source": "Brasil 247",
        "title": "Rússia lança ataque contra a Ucrânia. Explosões são ouvidas em Kiev e Lviv - Brasil 247",
        "timestamp": "2026-01-09T03:24:00Z"
    },
    {
        "source": "Migalhas",
        "title": "Lula sanciona Código do Contribuinte e combate devedor contumaz - Migalhas",
        "timestamp": "2026-01-09T11:09:11Z"
    },
    {
        "source": "Defesa Civil do Rio Grande do Sul",
        "title": "Defesa Civil alerta: Condição de ALERTA para instabilidades atuam no Oeste, com tempestade, granizo e raios - Defesa Civil do Rio Grande do Sul",
        "timestamp": "2026-01-09T08:25:00Z"
    },
    {
        "source": "Valor Econômico",
        "title": "Venezuela anuncia libertação de presos políticos e cita Lula - Valor Econômico",
        "timestamp": "2026-01-08T18:00:31Z"
    },
    {
        "source": "BBC",
        "title": "Ameaça de ação militar dos EUA contra a Colômbia é 'real', diz presidente do país à BBC - BBC",
        "timestamp": "2026-01-09T11:37:30Z"
    },
    {
        "source": "Migalhas",
        "title": "Advogada é presa pela sexta vez por furto de bebidas em supermercado - Migalhas",
        "timestamp": "2026-01-09T12:24:32Z"
    }
]