[
    {
        "source": "Senado Federal",
        "title": "Lei autoriza pagamento a servidores de benefícios congelados na pandemia - Senado Federal",
        "timestamp": "2026-01-13T13:38:20Z"
    },
    {
        "source": "CartaCapital",
        "title": "A disputa eleitoral para a presidência, segundo nova pesquisa - CartaCapital",
        "timestamp": "2026-01-13T11:07:00Z"
    },
    {
        "source": "UOL Notícias",
        "title": "Garoto que se vestiu de nazista em formatura pede desculpa: 'Estou errado' - UOL Notícias",
        "timestamp": "2026-01-13T13:08:02Z"
    },
    {
        "source": "BBC",
        "title": "José Manuel da Conceição: o padre que se tornou o primeiro pastor evangélico brasileiro - BBC",
        "timestamp": "2026-01-13T10:18:45Z"
    },
    {
        "source": "Gazeta do Povo",
        "title": "Promotores desistem do combate à corrupção diante da impunidade - Gazeta do Povo",
        "timestamp": "2026-01-13T00:35:00Z"
    },
    {
        "source": "GOV.BR",
        "title": "Mais Professores para o Brasil: governo institui política nacional para impulsionar a docência na Educação Básica - GOV.BR",
        "timestamp": "2026-01-13T13:16:26Z"
    }
]