[
    {
        "source": "G1",
        "title": "Quem é o motorista da carreta com falsa bomba que interditou o Rodoanel por quase 5 horas - G1",
        "timestamp": "2025-11-12T14:53:53Z"
    },
    {
        "source": "CNN Brasil",
        "title": "Ministério critica divulgação de transferência de presos; Castro rebate - CNN Brasil",
        "timestamp": "2025-11-12T16:56:58Z"
    },
    {
        "source": "Poder360",
        "title": "Lewandowski sobre Derrite: \"Surpreendidos por relatório feito em 24h” - Poder360",
        "timestamp": "2025-11-12T01:12:23Z"
    },
    {
        "source": "Poder360",
        "title": "Rejeição a Tarcísio é menor do que a Lula e à família Bolsonaro - Poder360",
        "timestamp": "2025-11-12T10:01:58Z"
    },
    {
        "source": "Gazeta do Povo",
        "title": "Gonet discute com a oposição e diz que PGR não faz “denúncias precipitadas” - Gazeta do Povo",
        "timestamp": "2025-11-12T12:47:00Z"
    },
    {
        "source": "UOL Notícias",
        "title": "Jamil Chade: Safári humano: inquérito apura turismo europeu para matar civis na Bósnia - UOL Notícias",
        "timestamp": "2025-11-12T15:02:27Z"
    }
]