[
    {
        "source": "G1",
        "title": "Em derrota para Trump, Suprema Corte dos EUA mantém cidadania por nascimento - G1",
        "timestamp": "2026-06-30T14:34:17Z"
    },
    {
        "source": "G1",
        "title": "TRT e MP sugerem trégua na greve dos rodoviários; sindicato se reúne para avaliar proposta - G1",
        "timestamp": "2026-06-30T15:39:15Z"
    },
    {
        "source": "BBC",
        "title": "Mãe resgatada com bebê de 18 dias após terremoto na Venezuela: 'Ele foi meu motor para continuar viva' - BBC",
        "timestamp": "2026-06-29T22:21:03Z"
    },
    {
        "source": "Brasil 247",
        "title": "Lula anuncia aporte de US$ 100 milhões para fundo do Mercosul - Brasil 247",
        "timestamp": "2026-06-29T17:05:17Z"
    },
    {
        "source": "G1",
        "title": "Nunes Marques dá quarto voto para liberação mais ampla de penduricalhos; placar está 5x4 - G1",
        "timestamp": "2026-06-29T14:50:12Z"
    },
    {
        "source": "Poder360",
        "title": "Valdemar se reúne com Michelle após vídeo sobre Flávio Bolsonaro - Poder360",
        "timestamp": "2026-06-30T13:24:01Z"
    }
]