[
    {
        "source": "Valor Econômico",
        "title": "Motta segue Alcolumbre e anuncia rompimento com líder do PT - Valor Econômico",
        "timestamp": "2025-11-24T17:55:20Z"
    },
    {
        "source": "Poder360",
        "title": "Tornozeleira violada por Bolsonaro deve ser paga pelo governo de Ibaneis - Poder360",
        "timestamp": "2025-11-24T17:37:30Z"
    },
    {
        "source": "O Globo",
        "title": "Filhos de Bolsonaro se reúnem com aliados após prisão, e Flávio e Michelle devem centralizar articulações - O Globo",
        "timestamp": "2025-11-24T11:00:34Z"
    },
    {
        "source": "O Globo",
        "title": "Na prisão, Bolsonaro recusa comida da PF e recebe refeições levadas por familiares - O Globo",
        "timestamp": "2025-11-24T12:04:23Z"
    },
    {
        "source": "Poder360",
        "title": "COP30 colecionou flops que foram além do documento final - Poder360",
        "timestamp": "2025-11-24T09:04:19Z"
    },
    {
        "source": "Valor Econômico",
        "title": "Lula diz que Brasil não será exportador de minerais críticos: se quiser, terá que industrializar nosso país - Valor Econômico",
        "timestamp": "2025-11-24T14:48:24Z"
    }
]