[
    {
        "source": "Folha PE",
        "title": "EUA sofrem golpe inédito em 20 anos com derrubada de aviões no Irã - Folha PE",
        "timestamp": "2026-04-04T11:42:00Z"
    },
    {
        "source": "CNN Brasil",
        "title": "Trump dá ultimato de 48 horas ao Irã e ameaça “Inferno” - CNN Brasil",
        "timestamp": "2026-04-04T15:03:43Z"
    },
    {
        "source": "O Globo",
        "title": "Imprensa argentina trata caso de Agostina Páez como 'escândalo sem fim' após pai reproduzir gestos racistas - O Globo",
        "timestamp": "2026-04-04T13:07:53Z"
    },
    {
        "source": "Brasil 247",
        "title": "PL, de Valdemar, se consolida com a maior bancada, com 101 deputados; PT vem em segundo - Brasil 247",
        "timestamp": "2026-04-04T08:24:04Z"
    },
    {
        "source": "Brasil 247",
        "title": "Estreito de Ormuz enfrenta colapso e tráfego cai de 130 navios por dia para 221 em um mês - Brasil 247",
        "timestamp": "2026-04-03T22:38:09Z"
    },
    {
        "source": "NSC Total",
        "title": "Casal morto em acidente fazia voo de teste para comprar avião que caiu no RS - NSC Total",
        "timestamp": "2026-04-04T13:53:37Z"
    }
]