[
    {
        "source": "O Globo",
        "title": "Governo Lula anuncia que bancos terão que congelar recursos de bets ilegais - O Globo",
        "timestamp": "2026-06-19T17:00:46Z"
    },
    {
        "source": "CNN Brasil",
        "title": "Governistas alinham discurso para descolar imagem de Lula de Jaques Wagner - CNN Brasil",
        "timestamp": "2026-06-19T06:31:18Z"
    },
    {
        "source": "G1",
        "title": "Trump diz que Meloni 'implorou' por foto com ele; premiê italiana nega: 'Declarações completamente inventadas' - G1",
        "timestamp": "2026-06-19T11:54:50Z"
    },
    {
        "source": "CartaCapital",
        "title": "Operação mira esquema de descontos em folha de servidores do DF e tem BRB, PicPay e ex-dirigentes entre os alvos - CartaCapital",
        "timestamp": "2026-06-19T12:03:00Z"
    },
    {
        "source": "O Globo",
        "title": "Rio das Pedras, última base da milícia na região, é alvo do CV, que quer formar 'cinturão'; entenda a disputa territorial - O Globo",
        "timestamp": "2026-06-19T13:29:14Z"
    },
    {
        "source": "Folha de S.Paulo",
        "title": "Brasil tem 8,4 milhões que não sabem ler nem escrever, mais da metade no Nordeste - Folha de S.Paulo",
        "timestamp": "2026-06-19T13:00:00Z"
    }
]