[
    {
        "source": "O GLOBO",
        "title": "Hotel de onde Trump foi retirado após disparos neste sábado é o mesmo em que Reagan sofreu atentado em 1981 - O GLOBO",
        "timestamp": "2026-04-26T04:07:02Z"
    },
    {
        "source": "Poder360",
        "title": "Zema ironiza Gilmar, Moraes e voos em jatinhos em novo vídeo - Poder360",
        "timestamp": "2026-04-26T00:23:15Z"
    },
    {
        "source": "Correio Braziliense",
        "title": "PT prepara alianças para reeleição de Lula em congresso nacional - Correio Braziliense",
        "timestamp": "2026-04-25T13:36:00Z"
    },
    {
        "source": "estadao.com.br",
        "title": "Nikolas Ferreira diz que capacidade cognitiva de filho de Bolsonaro é menor que de ‘toupeira cega’ - estadao.com.br",
        "timestamp": "2026-04-24T22:42:38Z"
    },
    {
        "source": "Poder360",
        "title": "Sem 6 X 1, comércio “vai poder contratar folguista”, diz Boulos - Poder360",
        "timestamp": "2026-04-25T16:58:06Z"
    },
    {
        "source": "O Antagonista",
        "title": "Se eu tivesse juízo não disputaria mais a Presidência, diz Ciro Gomes - O Antagonista",
        "timestamp": "2026-04-25T18:32:00Z"
    }
]