[
    {
        "source": "Correio Braziliense",
        "title": "STF forma maioria para manter prisão preventiva de Jair Bolsonaro - Correio Braziliense",
        "timestamp": "2025-11-24T13:31:00Z"
    },
    {
        "source": "O Antagonista",
        "title": "Crusoé: Família Bolsonaro sai de cena e o jogo muda - O Antagonista",
        "timestamp": "2025-11-24T10:27:00Z"
    },
    {
        "source": "Poder360",
        "title": "Brasil “se perdeu por caminhos sombrios”, diz Lula - Poder360",
        "timestamp": "2025-11-24T11:44:21Z"
    },
    {
        "source": "NSC Total",
        "title": "Quem era o piloto que morreu após acidente em show radical do Beto Carrero World - NSC Total",
        "timestamp": "2025-11-24T14:04:15Z"
    },
    {
        "source": "Poder360",
        "title": "COP30 colecionou flops que foram além do documento final - Poder360",
        "timestamp": "2025-11-24T09:04:19Z"
    },
    {
        "source": "Revista Oeste",
        "title": "Com dificuldades para aprovação ao STF, Messias envia carta a Alcolumbre - Revista Oeste",
        "timestamp": "2025-11-24T13:18:54Z"
    }
]