[
    {
        "source": "Valor Econômico",
        "title": "Exclusivo: Allianz deixa de nomear estádio do Palmeiras com mudança de estratégia no país - Valor Econômico",
        "timestamp": "2026-04-10T13:54:01Z"
    },
    {
        "source": "G1",
        "title": "Por que governo Trump voltou a atacar o Pix (e o que EUA podem fazer contra ele)? - G1",
        "timestamp": "2026-04-10T08:35:24Z"
    },
    {
        "source": "Revista Oeste",
        "title": "Exército prende militares por ordem de Moraes - Revista Oeste",
        "timestamp": "2026-04-10T12:26:14Z"
    },
    {
        "source": "Poder360",
        "title": "Trump diz que Irã não pode cobrar taxa de navegação em Ormuz - Poder360",
        "timestamp": "2026-04-10T01:42:55Z"
    },
    {
        "source": "UOL Notícias",
        "title": "Aliados veem briga entre Eduardo e Nikolas com 'potencial catastrófico' - UOL Notícias",
        "timestamp": "2026-04-10T08:30:00Z"
    },
    {
        "source": "CNN Brasil",
        "title": "Líbano ordena retirada de armas de grupos armados em Beirute - CNN Brasil",
        "timestamp": "2026-04-09T16:21:47Z"
    }
]