[
    {
        "source": "Valor Econômico",
        "title": "FT: Trump alerta que Otan terá ‘futuro muito ruim’ se não ajudar EUA a reabrir Ormuz - Valor Econômico",
        "timestamp": "2026-03-16T00:24:02Z"
    },
    {
        "source": "Revista Oeste",
        "title": "Master: começa a corrida pela 1ª delação premiada - Revista Oeste",
        "timestamp": "2026-03-16T11:06:45Z"
    },
    {
        "source": "G1",
        "title": "Mulher morre após ter carro atingido em troca de tiros durante perseguição em Cascadura - G1",
        "timestamp": "2026-03-16T00:17:17Z"
    },
    {
        "source": "Notícias da TV",
        "title": "O recado de Tânia Maria para Wagner Moura após O Agente Secreto ficar sem Oscar - Notícias da TV",
        "timestamp": "2026-03-16T10:10:00Z"
    },
    {
        "source": "Jovem Pan",
        "title": "Imposto de Renda 2026: Receita define datas de pagamento de restituições - Jovem Pan",
        "timestamp": "2026-03-16T11:43:40Z"
    },
    {
        "source": "Poder360",
        "title": "Bolsonaro tem piora com aumento de marcadores de inflamação no sangue - Poder360",
        "timestamp": "2026-03-15T15:54:21Z"
    }
]