[
    {
        "source": "G1",
        "title": "Lula sobre fraudes no INSS: 'Se tiver filho meu envolvido nisso, será investigado' - G1",
        "timestamp": "2025-12-18T15:42:37Z"
    },
    {
        "source": "Agência Brasil",
        "title": "Lula afirma que vai vetar PL da Dosimetria - Agência Brasil",
        "timestamp": "2025-12-18T16:00:00Z"
    },
    {
        "source": "BBC",
        "title": "Escala 6x1, Trump, Venezuela e acordo UE-Mercosul: os recados da entrevista de Lula - BBC",
        "timestamp": "2025-12-18T17:06:01Z"
    },
    {
        "source": "Migalhas",
        "title": "STF julga fixação de idade mínima para aposentadoria especial do INSS - Migalhas",
        "timestamp": "2025-12-18T18:23:22Z"
    },
    {
        "source": "Portal da Câmara dos Deputados",
        "title": "Congresso adia para esta sexta-feira sessão para votar Orçamento de 2026 e créditos suplementares - Portal da Câmara dos Deputados",
        "timestamp": "2025-12-18T14:57:00Z"
    },
    {
        "source": "www.gov.br",
        "title": "Detrans de todas as regiões do país já operam modelo da CNH do Brasil — Ministério dos Transportes - www.gov.br",
        "timestamp": "2025-12-18T12:21:00Z"
    }
]