[
    {
        "source": "CNN Brasil",
        "title": "Brasil, China e Reino Unido: Veja 60 economias que podem ter taxa dos EUA - CNN Brasil",
        "timestamp": "2026-06-03T11:45:16Z"
    },
    {
        "source": "CNN Brasil",
        "title": "Defesa de Vorcaro apresenta nova proposta de delação - CNN Brasil",
        "timestamp": "2026-06-03T17:03:49Z"
    },
    {
        "source": "O Globo",
        "title": "Caso Henry: promotor diz que Jairinho ligou cinco vezes para Monique na madrugada da morte do menino - O Globo",
        "timestamp": "2026-06-03T15:15:06Z"
    },
    {
        "source": "Brasil 247",
        "title": "Farra de Vorcaro para autoridades brasileiras com russas e ucranianas em Nova York custou quase R$ 12 milhões - Brasil 247",
        "timestamp": "2026-06-03T08:08:16Z"
    },
    {
        "source": "Poder360",
        "title": "53% defendem classificar PCC e CV como “terroristas” - Poder360",
        "timestamp": "2026-06-03T09:45:52Z"
    },
    {
        "source": "CNN Brasil",
        "title": "Greve geral em Portugal paralisa trens, voos e fecha escolas - CNN Brasil",
        "timestamp": "2026-06-03T14:03:13Z"
    }
]