[
    {
        "source": "Poder360",
        "title": "Governo avalia ir ao STF contra derrubada de vetos ao licenciamento - Poder360",
        "timestamp": "2025-11-27T22:49:54Z"
    },
    {
        "source": "CNN Brasil",
        "title": "Ex-número 2 de Ciro Nogueira é alvo de operação contra sonegação fiscal - CNN Brasil",
        "timestamp": "2025-11-27T19:26:30Z"
    },
    {
        "source": "Jovem Pan",
        "title": "PL corta salário de Bolsonaro para cumprir lei: ‘Infelizmente’ - Jovem Pan",
        "timestamp": "2025-11-27T21:07:41Z"
    },
    {
        "source": "G1",
        "title": "Congresso Nacional derruba vetos ao Propag, que pode reduzir déficit do RJ em R$ 8 bilhões - G1",
        "timestamp": "2025-11-27T15:42:01Z"
    },
    {
        "source": "ICL Notícias",
        "title": "Sob pressão, Hugo Motta anuncia relator de lei que combate devedor contumaz - ICL Notícias",
        "timestamp": "2025-11-28T00:04:29Z"
    },
    {
        "source": "CartaCapital",
        "title": "A resposta de Cármen Lúcia aos habeas corpus para Bolsonaro no STF - CartaCapital",
        "timestamp": "2025-11-28T00:54:00Z"
    }
]