[
    {
        "source": "cnnbrasil.com.br",
        "title": "Atirador em jantar de Trump é homem de 31 anos da Califórnia, dizem fontes - cnnbrasil.com.br",
        "timestamp": "2026-04-26T02:34:30Z"
    },
    {
        "source": "estadao.com.br",
        "title": "Zema cresce e aparece às custas de STF e rejeição de Lula e Bolsonaro - estadao.com.br",
        "timestamp": "2026-04-25T23:00:00Z"
    },
    {
        "source": "Poder360",
        "title": "Flávio Bolsonaro pede fim de cobranças entre aliados do PL - Poder360",
        "timestamp": "2026-04-25T19:30:35Z"
    },
    {
        "source": "Revista Oeste",
        "title": "Mulher que ficou 8 dias desaparecida em SC é suspeita de desviar R$ 40 mil - Revista Oeste",
        "timestamp": "2026-04-26T02:00:00Z"
    },
    {
        "source": "Jovem Pan",
        "title": "Irã entrega exigências para acordo de cessar-fogo no Oriente Médio - Jovem Pan",
        "timestamp": "2026-04-25T13:40:00Z"
    },
    {
        "source": "Poder360",
        "title": "Sem 6 X 1, comércio “vai poder contratar folguista”, diz Boulos - Poder360",
        "timestamp": "2026-04-25T16:58:06Z"
    }
]