[
    {
        "source": "O Globo",
        "title": "Vídeo mostra momento em que ônibus que levava torcedores do Flamengo para a Argentina capota - O Globo",
        "timestamp": "2025-10-27T20:47:10Z"
    },
    {
        "source": "Correio Braziliense",
        "title": "Advogado de Trump critica Lula após encontro: 'Desesperado por validação' - Correio Braziliense",
        "timestamp": "2025-10-27T18:32:37Z"
    },
    {
        "source": "Correio do Povo",
        "title": "Por que os argentinos deram seu apoio a Milei nas eleições legislativas? - Correio do Povo",
        "timestamp": "2025-10-27T16:01:45Z"
    },
    {
        "source": "CartaCapital",
        "title": "Trama golpista: Prazo para defesa de Bolsonaro apresentar recursos termina nesta segunda; saiba o que vem a seguir - CartaCapital",
        "timestamp": "2025-10-27T10:39:00Z"
    },
    {
        "source": "O Globo",
        "title": "'Excede a capacidade do Estado do Rio de Janeiro', afirma porta-voz da PM sobre confronto entre facções rivais na região da Pedreira e do Chapadão - O Globo",
        "timestamp": "2025-10-27T15:29:55Z"
    },
    {
        "source": "MetSul Meteorologia",
        "title": "O que meteorologistas encontraram no olho do furacão monstro no Caribe; veja vídeo - MetSul Meteorologia",
        "timestamp": "2025-10-27T16:55:51Z"
    }
]