[
    {
        "source": "Jovem Pan",
        "title": "Fazenda vê fim da 6×1 maduro no Congresso, mas texto pode afastar governo - Jovem Pan",
        "timestamp": "2026-02-15T11:40:28Z"
    },
    {
        "source": "UOL Notícias",
        "title": "Josias de Souza: Apoio de Ciro Nogueira a Toffoli cai no ridículo com racha do PP - UOL Notícias",
        "timestamp": "2026-02-15T22:23:10Z"
    },
    {
        "source": "CartaCapital",
        "title": "Merz cita ordem mundial ‘sob destruição’ e acena ao Brasil - CartaCapital",
        "timestamp": "2026-02-14T11:28:00Z"
    },
    {
        "source": "Estado de Minas",
        "title": "Ativista de esquerda provoca foliões no Bloco da Anistia - Estado de Minas",
        "timestamp": "2026-02-15T14:38:00Z"
    },
    {
        "source": "Correio Braziliense",
        "title": "Blocos de carnaval tomam as ruas do DF neste domingo (15); veja programação - Correio Braziliense",
        "timestamp": "2026-02-15T14:02:00Z"
    },
    {
        "source": "UOL Notícias",
        "title": "'Feminicídio indireto': caso Itumbiara expõe brecha na Lei Maria da Penha - UOL Notícias",
        "timestamp": "2026-02-15T13:30:00Z"
    }
]