[
    {
        "source": "CNN Brasil",
        "title": "Michelle, filhos de Bolsonaro e Ciro: entenda a crise do PL em cinco pontos - CNN Brasil",
        "timestamp": "2025-12-02T14:30:29Z"
    },
    {
        "source": "O Globo",
        "title": "Convite a Messias para almoço com senadores do PL gerou reclamações em grupo de WhatsApp da bancada - O Globo",
        "timestamp": "2025-12-02T15:32:43Z"
    },
    {
        "source": "CartaCapital",
        "title": "Pesquisa testa Lula contra Tarcísio, Michelle e Flávio para 2026; veja os resultados - CartaCapital",
        "timestamp": "2025-12-02T11:30:00Z"
    },
    {
        "source": "BBC",
        "title": "O jovem morto após invadir jaula de leoa em João Pessoa: 'A última etapa de uma tragédia anunciada' - BBC",
        "timestamp": "2025-12-02T12:22:30Z"
    },
    {
        "source": "Correio Braziliense",
        "title": "Polícia Federal investiga parlamentares sob suspeita no Caso Master - Correio Braziliense",
        "timestamp": "2025-12-02T01:12:00Z"
    },
    {
        "source": "Poder360",
        "title": "Trump diz que Honduras tenta mudar resultado de eleição - Poder360",
        "timestamp": "2025-12-02T08:51:42Z"
    }
]