[
    {
        "source": "Agência Brasil",
        "title": "Polícia do Paraguai entrega Silvinei Vasques à PF - Agência Brasil",
        "timestamp": "2025-12-26T23:51:00Z"
    },
    {
        "source": "Agência Brasil",
        "title": "Bolsonaro inicia reabilitação pós-operatória - Agência Brasil",
        "timestamp": "2025-12-26T19:09:00Z"
    },
    {
        "source": "O Globo",
        "title": "Investigações em série: além de fraude com BRB, Banco Master é alvo de várias investigações. Veja quais - O Globo",
        "timestamp": "2025-12-27T07:00:40Z"
    },
    {
        "source": "BBC",
        "title": "Por que EUA lançaram 'ataques poderosos' contra Estado Islâmico na Nigéria, segundo Trump - BBC",
        "timestamp": "2025-12-26T11:25:29Z"
    },
    {
        "source": "GOV.BR",
        "title": "RELATÓRIO ESPECIAL DA CIDH SOBRE A SITUAÇÃO DA LIBERDADE DE EXPRESSÃO NO BRASIL - GOV.BR",
        "timestamp": "2025-12-26T19:37:30Z"
    },
    {
        "source": "Agência Brasil",
        "title": "Corpo humano não funciona como deveria em temperatura acima de 35°C - Agência Brasil",
        "timestamp": "2025-12-26T18:21:00Z"
    }
]