[
    {
        "source": "CNN Brasil",
        "title": "Trump diz que pontos finais de acordo entre EUA e Irã foram aprovados - CNN Brasil",
        "timestamp": "2026-06-11T17:47:34Z"
    },
    {
        "source": "O Globo",
        "title": "Caso Henry Borel: advogada deixa defesa de Monique em meio à disputa judicial sobre perdão concedido pela juíza - O Globo",
        "timestamp": "2026-06-11T21:42:16Z"
    },
    {
        "source": "Poder360",
        "title": "Alcolumbre não quer senador do PT para relatar PEC do fim da 6 X 1 - Poder360",
        "timestamp": "2026-06-11T09:03:45Z"
    },
    {
        "source": "Secretaria de Estado da Proteção e Defesa Civil",
        "title": "NOTA METEOROLÓGICA SDC/SC 11/06 – NOAA confirma o início do fenômeno El Niño - Secretaria de Estado da Proteção e Defesa Civil",
        "timestamp": "2026-06-11T17:55:27Z"
    },
    {
        "source": "CNN Brasil",
        "title": "STF forma maioria para fixar prazo de 60 dias para big techs se adequarem - CNN Brasil",
        "timestamp": "2026-06-11T21:42:20Z"
    },
    {
        "source": "CartaCapital",
        "title": "A vantagem de Lula na disputa com Flávio Bolsonaro em Pernambuco, segundo pesquisa - CartaCapital",
        "timestamp": "2026-06-11T10:55:00Z"
    }
]