[
    {
        "source": "O Globo",
        "title": "CV e PCC como terroristas: reação de Lula com ataques ao clã Bolsonaro eleva embate eleitoral sobre decisão dos EUA - O Globo",
        "timestamp": "2026-05-30T06:30:35Z"
    },
    {
        "source": "O Globo",
        "title": "Caso Henry: perícia descarta acidente doméstico, Jairinho e Monique deixam plenário, e depoimento de Leniel avança a madrugada; veja destaques do quinto dia de julgamento - O Globo",
        "timestamp": "2026-05-30T06:58:46Z"
    },
    {
        "source": "Folha de S.Paulo",
        "title": "Opinião - Marcos Mendes: Fim da escala 6x1 põe Brasil na marcha a ré - Folha de S.Paulo",
        "timestamp": "2026-05-29T23:54:00Z"
    },
    {
        "source": "Valor Econômico",
        "title": "PF envia a PGR parecer para investigar remessa de Vorcaro aos EUA a pedido de Flávio - Valor Econômico",
        "timestamp": "2026-05-29T21:17:21Z"
    },
    {
        "source": "JOTA",
        "title": "Agregador do JOTA: favoritismo de Lula cresce e atinge pico neste ciclo eleitoral - JOTA",
        "timestamp": "2026-05-29T13:00:27Z"
    },
    {
        "source": "CNN Brasil",
        "title": "Morre o filósofo Edgar Morin aos 104; pesquisadores brasileiros lamentam - CNN Brasil",
        "timestamp": "2026-05-29T21:41:45Z"
    }
]