[
    {
        "source": "CartaCapital",
        "title": "Lula e Macron se reúnem para discutir o combate ao narcotráfico e ao garimpo ilegal - CartaCapital",
        "timestamp": "2026-02-19T17:50:00Z"
    },
    {
        "source": "O Globo",
        "title": "Chapa dividida: após emplacar vice de Paes, que é aliado de Lula, Washington Reis diz que fará campanha para Flávio Bolsonaro - O Globo",
        "timestamp": "2026-02-19T19:28:38Z"
    },
    {
        "source": "Revista Oeste",
        "title": "Israel entra em alerta máximo com possível ataque dos EUA ao Irã - Revista Oeste",
        "timestamp": "2026-02-18T20:41:44Z"
    },
    {
        "source": "BBC",
        "title": "Fim da escala 6x1: consumidor rejeitará mudança quando entender que vai pagar a conta, diz presidente de associação de bares e restaurantes - BBC",
        "timestamp": "2026-02-19T08:44:53Z"
    },
    {
        "source": "UOL Notícias",
        "title": "Mulher de Moraes descobre entupimento em exame no coração e coloca stents - UOL Notícias",
        "timestamp": "2026-02-20T00:02:07Z"
    },
    {
        "source": "O Antagonista",
        "title": "PL Antifacção tranca pauta da Câmara dos Deputados - O Antagonista",
        "timestamp": "2026-02-19T16:53:00Z"
    }
]