[
    {
        "source": "G1",
        "title": "Superlotação em bloco com Calvin Harris em SP provoca tumulto, foliões passam mal e PM intensifica efetivo - G1",
        "timestamp": "2026-02-08T19:27:23Z"
    },
    {
        "source": "CNN Brasil",
        "title": "Foto de cueca e e-mails com Epstein: o escândalo que abala o Reino Unido - CNN Brasil",
        "timestamp": "2026-02-07T14:26:07Z"
    },
    {
        "source": "G1",
        "title": "Entenda as consequências de eventuais punições aos réus da trama golpista no STM - G1",
        "timestamp": "2026-02-08T07:01:27Z"
    },
    {
        "source": "G1",
        "title": "Polícia investiga morte de mulher após nadar em piscina de academia na Zona Leste - G1",
        "timestamp": "2026-02-08T13:55:05Z"
    },
    {
        "source": "Jornal Correio",
        "title": "Mar de gente: Baiana System fecha Furdunço arrastando multidão em Salvador - Jornal Correio",
        "timestamp": "2026-02-08T09:30:00Z"
    },
    {
        "source": "VEJA",
        "title": "“Querem me matar”, diz advogada da Argentina acusada de injúria racial - VEJA",
        "timestamp": "2026-02-08T17:10:26Z"
    }
]