[
    {
        "source": "Poder360",
        "title": "EUA vão intensificar ataques ao Irã nas próximas 3 semanas, diz Trump - Poder360",
        "timestamp": "2026-04-02T04:18:22Z"
    },
    {
        "source": "folha.uol.com.br",
        "title": "Grandes distribuidoras de combustíveis decidem ficar fora de programa de subvenção ao diesel - folha.uol.com.br",
        "timestamp": "2026-04-02T02:00:00Z"
    },
    {
        "source": "Diário do Poder",
        "title": "Lula não cumpriu promessa de indicar Pacheco para o STF, irritando Alcolumbre - Diário do Poder",
        "timestamp": "2026-04-02T01:50:00Z"
    },
    {
        "source": "O Globo",
        "title": "EUA voltam a criticar Pix, 25 de Março e restrições do Brasil a big techs em relatório comercial - O Globo",
        "timestamp": "2026-04-01T23:09:44Z"
    },
    {
        "source": "CNN Brasil",
        "title": "Golpistas usam morte de filho de humorista no Rio para pedir dinheiro - CNN Brasil",
        "timestamp": "2026-04-01T17:22:40Z"
    },
    {
        "source": "CartaCapital",
        "title": "Irã promete ataques ‘devastadores’ contra EUA e Israel após ameaças de Trump - CartaCapital",
        "timestamp": "2026-04-02T09:51:00Z"
    }
]