[
    {
        "source": "CartaCapital",
        "title": "Como Flávio Bolsonaro implodiu o compromisso de Valdemar com o TSE para a eleição - CartaCapital",
        "timestamp": "2026-07-22T17:16:00Z"
    },
    {
        "source": "G1",
        "title": "'Há males que vêm para o bem', diz Lula em cerimônia de anúncio de medidas de resposta ao tarifaço dos EUA - G1",
        "timestamp": "2026-07-22T18:55:50Z"
    },
    {
        "source": "CNN Brasil",
        "title": "EUA assinam acordo com Arábia Saudita que pode permitir combustível nuclear - CNN Brasil",
        "timestamp": "2026-07-22T21:44:21Z"
    },
    {
        "source": "O GLOBO",
        "title": "Ciro Nogueira avisa Flávio Bolsonaro que PP ficará neutro na eleição presidencial e frustra PL - O GLOBO",
        "timestamp": "2026-07-22T18:29:28Z"
    },
    {
        "source": "O GLOBO",
        "title": "Ônibus superlotado tem janelas e vidros quebrados durante confusão em Copacabana - O GLOBO",
        "timestamp": "2026-07-22T21:46:29Z"
    },
    {
        "source": "Poder360",
        "title": "EUA lançam ataques contra o Irã pela 11ª noite consecutiva - Poder360",
        "timestamp": "2026-07-22T09:39:50Z"
    }
]