[
    {
        "source": "Valor Econômico",
        "title": "Alexandre de Moraes procurou presidente do BC para pedir por Banco Master, diz jornal - Valor Econômico",
        "timestamp": "2025-12-22T15:26:21Z"
    },
    {
        "source": "Migalhas",
        "title": "Lula sanciona aumento do Judiciário para 2026 e veta reajustes futuros - Migalhas",
        "timestamp": "2025-12-22T17:01:55Z"
    },
    {
        "source": "Agência Brasil",
        "title": "Câmara cancela passaporte diplomático de Eduardo Bolsonaro e Ramagem - Agência Brasil",
        "timestamp": "2025-12-22T18:14:00Z"
    },
    {
        "source": "CNN Brasil",
        "title": "Rússia promete apoio à Venezuela contra bloqueio dos EUA, diz ministro - CNN Brasil",
        "timestamp": "2025-12-22T16:09:15Z"
    },
    {
        "source": "Defesa Civil do Rio Grande do Sul",
        "title": "Defesa Civil alerta: Condição de ALERTA para chuva, vento e raios - Defesa Civil do Rio Grande do Sul",
        "timestamp": "2025-12-22T18:32:44Z"
    },
    {
        "source": "BBC",
        "title": "Caso Jeffrey Epstein: Foto de Trump é reinserida nos arquivos após acusações de 'acobertamento' - BBC",
        "timestamp": "2025-12-22T14:40:52Z"
    }
]