[
    {
        "source": "G1",
        "title": "Quaest: 64% dos moradores do RJ aprovam megaoperação nos complexos do Alemão e da Penha - G1",
        "timestamp": "2025-11-01T23:34:49Z"
    },
    {
        "source": "NSC Total",
        "title": "Jovem morta baleada dentro de carro no RJ compartilhou reflexão horas antes do tiroteio - NSC Total",
        "timestamp": "2025-11-01T19:43:00Z"
    },
    {
        "source": "VEJA",
        "title": "Em plano antifacção, governo cogitou barrar medida que beneficiou líder do CV - VEJA",
        "timestamp": "2025-11-01T13:30:12Z"
    },
    {
        "source": "G1",
        "title": "Vídeo gravado por policial do Bope mostra o momento do confronto com traficantes no Rio de Janeiro - G1",
        "timestamp": "2025-11-01T23:35:52Z"
    },
    {
        "source": "Poder360",
        "title": "Aprovação de Castro bate recorde após megaoperação no Rio - Poder360",
        "timestamp": "2025-11-01T20:25:41Z"
    },
    {
        "source": "Correio Braziliense",
        "title": "Lula chega a Belém para inaugurar obras e participar de eventos da COP30 - Correio Braziliense",
        "timestamp": "2025-11-01T13:08:00Z"
    }
]